dotnetinteropt/__init__.py
dotnetinteropt/_version.py
dotnetinteropt/backend.py
dotnetinteropt/frontend.py
dotnetinteropt/loader.py
dotnetinteropt-0.2.0.dist-info/LICENSE
dotnetinteropt-0.2.0.dist-info/METADATA
dotnetinteropt-0.2.0.dist-info/WHEEL
dotnetinteropt-0.2.0.dist-info/entry_points.txt
dotnetinteropt-0.2.0.dist-info/top_level.txt
dotnetinteropt-0.2.0.dist-info/RECORD
